e621/__init__.py
e621/api.py
e621/autogenerated_models.py
e621/base_model.py
e621/endpoints.py
e621/enums.py
e621/models.py
e621/py.typed
e621/session.py
e621/util.py
e621_temp-1.0.7.dist-info/LICENSE
e621_temp-1.0.7.dist-info/WHEEL
e621_temp-1.0.7.dist-info/METADATA
e621_temp-1.0.7.dist-info/RECORD
